iisi/__about__.py
iisi/__init__.py
iisi/application.py
iisi/authorizer.py
iisi/container.py
iisi/context.py
iisi/entities.py
iisi/exception.py
iisi/principal.py
iisi/routes.py
iisi/usecase.py
iisi/value_objects.py
iisi/domain/__init__.py
iisi/domain/component.py
iisi/domain/usecasestack.py
iisi/factories/__init__.py
iisi/factories/factory.py
iisi/factories/repository.py
iisi/handlers/__init__.py
iisi/handlers/handler.py
iisi/handlers/result.py
iisi/handlers/usecase.py
iisi/resolvers/__init__.py
iisi/resolvers/parameters.py
iisi/resolvers/principal.py
iisi/resolvers/resolver.py
iisi/resolvers/usecase.py
iisi_python-0.1.1.dist-info/METADATA
iisi_python-0.1.1.dist-info/WHEEL
iisi_python-0.1.1.dist-info/licenses/LICENSE
iisi_python-0.1.1.dist-info/RECORD
