Metadata-Version: 2.3
Name: iisi-python
Version: 0.1.1
Project-URL: Documentation, https://github.com/Iimiva/iisi#readme
Project-URL: Issues, https://github.com/Iimiva/iisi/issues
Project-URL: Source, https://github.com/Iimiva/iisi
Author-email: Iimiva <iiro.sinisalo@isinisalo.com>
License-Expression: MIT
License-File: LICENSE
Classifier: Development Status :: 4 - Beta
Classifier: Programming Language :: Python
Classifier: Programming Language :: Python :: 3.11
Classifier: Programming Language :: Python :: Implementation :: CPython
Classifier: Programming Language :: Python :: Implementation :: PyPy
Requires-Python: >=3.11
Requires-Dist: authoritah
Requires-Dist: punq
